{
  "id": "kuhnya-v-neone",
  "slug": "kuhnya-v-neone",
  "title": "Кухня в неоне",
  "artistId": "khorst",
  "artistName": "Вася Хорст",
  "artistSlug": "khorst",
  "year": 2024,
  "technique": "графика, риzo",
  "techniqueGroup": "graphics",
  "workType": "editioned",
  "price": 4800,
  "priceFormatted": "4 800 ₽",
  "status": "available",
  "editionTotal": 50,
  "editionNumber": 11,
  "availableCount": 39,
  "artistProofs": 0,
  "editionClosed": false,
  "sheetSize": "30 × 42 см",
  "imageSize": "",
  "paper": "Hahnemühle 300 г/м², фактурная",
  "signature": "карандашом, нижнее поле, справа",
  "condition": "Mint, не оформлено в раму",
  "certificate": "сертификат подлинности от издательства PRSTNK",
  "uniquenessNote": "",
  "dominantColor": "#FF3DA0",
  "shortDescription": "",
  "description": "",
  "mainImage": "",
  "galleryImages": [],
  "placeholderSvg": "placeholders/kuhnya-v-neone.svg",
  "alt": "графика, риzo, Кухня в неоне, Вася Хорст",
  "collections": [
    "under-10k",
    "color"
  ],
  "featuredOnHome": false,
  "featuredInCatalog": true,
  "telegramReserveText": "Хочу забронировать экземпляр №11/50 работы «Кухня в неоне» — Вася Хорст, 2024. Цена 4 800 ₽.",
  "seoTitle": "Вася Хорст. «Кухня в неоне», 2024 — графика, риzo 11/50 — PRSTNK",
  "seoDescription": "«Кухня в неоне» — графика, риzo, Вася Хорст, 2024. Тираж 50, лист 11/50, 30 × 42 см. Подпись и нумерация автора, сертификат. 4 800 ₽.",
  "order": 16
}